{"$id":"http://code-magic2.com/LiquidsConfiguration","definitions":{"ILiquidConfiguration":{"type":["object","null"],"properties":{"Type":{"type":["string","null"]},"FreezingPoint":{"type":"integer"},"BoilingPoint":{"type":"integer"},"MinVolumeForEffect":{"type":"integer"},"MaxVolumeBeforeSpread":{"type":"integer"},"MaxSpreadVolume":{"type":"integer"},"EvaporationMultiplier":{"type":"integer"},"EvaporationTemperatureMultiplier":{"type":"number"},"CondensationTemperatureMultiplier":{"type":"number"},"FreezingTemperatureMultiplier":{"type":"number"},"MeltingTemperatureMultiplier":{"type":"number"},"Steam":{"$ref":"#/definitions/ISteamConfiguration"},"CustomValues":{"type":["array","null"],"items":{"$ref":"#/definitions/ILiquidConfigurationCustomValue"}}},"required":["Type","FreezingPoint","BoilingPoint","MinVolumeForEffect","MaxVolumeBeforeSpread","MaxSpreadVolume","EvaporationMultiplier","EvaporationTemperatureMultiplier","CondensationTemperatureMultiplier","FreezingTemperatureMultiplier","MeltingTemperatureMultiplier","Steam","CustomValues"]},"ILiquidConfigurationCustomValue":{"type":["object","null"],"properties":{"Key":{"type":["string","null"]},"Value":{"type":["string","null"]}},"required":["Key","Value"]},"ISteamConfiguration":{"type":["object","null"],"properties":{"PressureMultiplier":{"type":"integer"},"ThicknessMultiplier":{"type":"number"},"MaxVolumeBeforeSpread":{"type":"integer"},"MaxSpreadVolume":{"type":"integer"}},"required":["PressureMultiplier","ThicknessMultiplier","MaxVolumeBeforeSpread","MaxSpreadVolume"]}},"type":"object","properties":{"LiquidsConfigurations":{"type":["array","null"],"items":{"$ref":"#/definitions/ILiquidConfiguration"}}},"required":["LiquidsConfigurations"]}